MANIFEST.in
README.md
requirements.txt
setup.py
sciencebeam_alignment/__init__.py
sciencebeam_alignment/align.py
sciencebeam_alignment/align_fast_utils.pyx
sciencebeam_alignment/align_performance.py
sciencebeam_alignment/levenshtein.py
sciencebeam_alignment/sequence_matcher.py
sciencebeam_alignment/word_sequence_matcher.py
sciencebeam_alignment.egg-info/PKG-INFO
sciencebeam_alignment.egg-info/SOURCES.txt
sciencebeam_alignment.egg-info/dependency_links.txt
sciencebeam_alignment.egg-info/requires.txt
sciencebeam_alignment.egg-info/top_level.txt
tests/__init__.py
tests/align_test.py
tests/conftest.py
tests/levenshtein_test.py
tests/word_sequence_matcher_test.py