Metadata-Version: 2.1
Name: sciencebeam-alignment
Version: 0.0.5
Summary: ScienceBeam Alignment
Home-page: https://github.com/elifesciences/sciencebeam-alignment
License: MIT
Keywords: sequence alignment
Platform: UNKNOWN
